smslib/__init__.py
smslib/notify.py
smslib/receiver.py
smslib/sender.py
smslib-1.0.0.dist-info/LICENSE
smslib-1.0.0.dist-info/METADATA
smslib-1.0.0.dist-info/WHEEL
smslib-1.0.0.dist-info/entry_points.txt
smslib-1.0.0.dist-info/top_level.txt
smslib-1.0.0.dist-info/RECORD
