Metadata-Version: 2.1
Name: smslib
Version: 1.0.0
Summary: Python library for sending SMS messages via email-to-SMS gateways
Author-email: Nathaniel Dene Hoffman <dene@cmu.edu>
License: MIT License
Project-URL: homepage, https://github.com/denehoffman/smslib
Project-URL: repository, https://github.com/denehoffman/smslib
Project-URL: documentation, https://github.com/denehoffman/smslib/blob/main/README.md
Keywords: SMS,text messages,email-to-SMS gateway
Classifier: License :: OSI Approved :: MIT License
Classifier: Development Status :: 5 - Production/Stable
Classifier: Intended Audience :: Developers
Classifier: Programming Language :: Python :: 3
Classifier: Programming Language :: Python :: 3.7
Classifier: Programming Language :: Python :: 3.8
Classifier: Programming Language :: Python :: 3.9
Classifier: Programming Language :: Python :: 3.10
Classifier: Programming Language :: Python :: 3.11
Classifier: Topic :: Communications :: Telephony
Classifier: Topic :: System :: Monitoring
Requires-Python: >=3.7
License-File: LICENSE
Requires-Dist: tomli (>=2.0.1) ; python_version < "3.11"
